<?xml version="1.0" encoding="utf-8" ?>
<dwsync>
<file name="dot_for_ie.gif" server="soundorthotics.brisksites.com//public_html/soundorthotics/" local="130597742241481078" remote="130597822200000000" Dst="1" />
<file name="icons.png" server="soundorthotics.brisksites.com//public_html/soundorthotics/" local="130597742239050939" remote="130597822200000000" Dst="1" />
<file name="style.css" server="soundorthotics.brisksites.com//public_html/soundorthotics/" local="130597742239150945" remote="130597822200000000" Dst="1" />
<file name="throbber.gif" server="soundorthotics.brisksites.com//public_html/soundorthotics/" local="130597742237660860" remote="130597822200000000" Dst="1" />
<file name="dot_for_ie.gif" server="ftp.soundorthotics.com//public_html/" local="130665029743198806" remote="130555676400000000" Dst="1" />
<file name="icons.png" server="ftp.soundorthotics.com//public_html/" local="130665029743228808" remote="130555676400000000" Dst="1" />
<file name="throbber.gif" server="ftp.soundorthotics.com//public_html/" local="130665029749969193" remote="130555676400000000" Dst="1" />
<file name="style.css" server="ftp.soundorthotics.com//public_html/" local="130665029750099201" remote="130555676400000000" Dst="1" />
</dwsync>